main.py
raise_tools-1.0.1.dist-info/LICENSE
raise_tools-1.0.1.dist-info/METADATA
raise_tools-1.0.1.dist-info/WHEEL
raise_tools-1.0.1.dist-info/entry_points.txt
raise_tools-1.0.1.dist-info/top_level.txt
raise_tools-1.0.1.dist-info/RECORD
