Metadata-Version: 2.1
Name: raise-tools
Version: 1.0.1
Summary: The RAISE lab code checker
Home-page: https://github.com/yrahul3910/raise-tools
Author: Rahul Yedida
Author-email: rahul@ryedida.me
Classifier: Programming Language :: Python :: 3
Classifier: License :: OSI Approved :: MIT License
Classifier: Operating System :: OS Independent
Requires-Python: >=3.6
License-File: LICENSE
Requires-Dist: colorama
Requires-Dist: pycodestyle
